odoo8_addon_purchase_partner_invoice_method-8.0.1.0.0.99.dev18-py3.8-nspkg.pth
odoo_addons/purchase_partner_invoice_method/__init__.py
odoo_addons/purchase_partner_invoice_method/__openerp__.py
odoo_addons/purchase_partner_invoice_method/partner.py
odoo_addons/purchase_partner_invoice_method/partner_demo.xml
odoo_addons/purchase_partner_invoice_method/partner_view.xml
odoo_addons/purchase_partner_invoice_method/purchase.py
odoo_addons/purchase_partner_invoice_method/i18n/am.po
odoo_addons/purchase_partner_invoice_method/i18n/ar.po
odoo_addons/purchase_partner_invoice_method/i18n/bg.po
odoo_addons/purchase_partner_invoice_method/i18n/bs.po
odoo_addons/purchase_partner_invoice_method/i18n/ca.po
odoo_addons/purchase_partner_invoice_method/i18n/cs.po
odoo_addons/purchase_partner_invoice_method/i18n/da.po
odoo_addons/purchase_partner_invoice_method/i18n/de.po
odoo_addons/purchase_partner_invoice_method/i18n/el_GR.po
odoo_addons/purchase_partner_invoice_method/i18n/en_GB.po
odoo_addons/purchase_partner_invoice_method/i18n/es.po
odoo_addons/purchase_partner_invoice_method/i18n/es_CR.po
odoo_addons/purchase_partner_invoice_method/i18n/es_EC.po
odoo_addons/purchase_partner_invoice_method/i18n/es_MX.po
odoo_addons/purchase_partner_invoice_method/i18n/es_VE.po
odoo_addons/purchase_partner_invoice_method/i18n/et.po
odoo_addons/purchase_partner_invoice_method/i18n/eu.po
odoo_addons/purchase_partner_invoice_method/i18n/fi.po
odoo_addons/purchase_partner_invoice_method/i18n/fr.po
odoo_addons/purchase_partner_invoice_method/i18n/fr_CH.po
odoo_addons/purchase_partner_invoice_method/i18n/fr_FR.po
odoo_addons/purchase_partner_invoice_method/i18n/gl.po
odoo_addons/purchase_partner_invoice_method/i18n/hr.po
odoo_addons/purchase_partner_invoice_method/i18n/hr_HR.po
odoo_addons/purchase_partner_invoice_method/i18n/hu.po
odoo_addons/purchase_partner_invoice_method/i18n/id.po
odoo_addons/purchase_partner_invoice_method/i18n/it.po
odoo_addons/purchase_partner_invoice_method/i18n/ja.po
odoo8_addon_purchase_partner_invoice_method-8.0.1.0.0.99.dev18.dist-info/METADATA
odoo8_addon_purchase_partner_invoice_method-8.0.1.0.0.99.dev18.dist-info/WHEEL
odoo8_addon_purchase_partner_invoice_method-8.0.1.0.0.99.dev18.dist-info/namespace_packages.txt
odoo8_addon_purchase_partner_invoice_method-8.0.1.0.0.99.dev18.dist-info/top_level.txt
odoo8_addon_purchase_partner_invoice_method-8.0.1.0.0.99.dev18.dist-info/RECORD
